odoo8_addon_web_widget_text_markdown-8.0.1.0.0.99.dev8-py2.7-nspkg.pth
odoo8_addon_web_widget_text_markdown-8.0.1.0.0.99.dev8.dist-info/DESCRIPTION.rst
odoo8_addon_web_widget_text_markdown-8.0.1.0.0.99.dev8.dist-info/METADATA
odoo8_addon_web_widget_text_markdown-8.0.1.0.0.99.dev8.dist-info/RECORD
odoo8_addon_web_widget_text_markdown-8.0.1.0.0.99.dev8.dist-info/WHEEL
odoo8_addon_web_widget_text_markdown-8.0.1.0.0.99.dev8.dist-info/metadata.json
odoo8_addon_web_widget_text_markdown-8.0.1.0.0.99.dev8.dist-info/namespace_packages.txt
odoo8_addon_web_widget_text_markdown-8.0.1.0.0.99.dev8.dist-info/top_level.txt
odoo_addons/web_widget_text_markdown/README.rst
odoo_addons/web_widget_text_markdown/__init__.py
odoo_addons/web_widget_text_markdown/__openerp__.py
odoo_addons/web_widget_text_markdown/i18n/ar.po
odoo_addons/web_widget_text_markdown/i18n/de.po
odoo_addons/web_widget_text_markdown/i18n/es.po
odoo_addons/web_widget_text_markdown/i18n/fi.po
odoo_addons/web_widget_text_markdown/i18n/fr.po
odoo_addons/web_widget_text_markdown/i18n/pt_BR.po
odoo_addons/web_widget_text_markdown/i18n/sl.po
odoo_addons/web_widget_text_markdown/i18n/tr.po
odoo_addons/web_widget_text_markdown/i18n/web_widget_text_markdown.pot
odoo_addons/web_widget_text_markdown/static/description/icon.png
odoo_addons/web_widget_text_markdown/static/lib/bootstrap-markdown/bootstrap-markdown.js
odoo_addons/web_widget_text_markdown/static/lib/highlight/CHANGES.md
odoo_addons/web_widget_text_markdown/static/lib/highlight/LICENSE
odoo_addons/web_widget_text_markdown/static/lib/highlight/README.md
odoo_addons/web_widget_text_markdown/static/lib/highlight/README.ru.md
odoo_addons/web_widget_text_markdown/static/lib/highlight/highlight.min.js
odoo_addons/web_widget_text_markdown/static/lib/highlight/styles/arta.css
odoo_addons/web_widget_text_markdown/static/lib/highlight/styles/ascetic.css
odoo_addons/web_widget_text_markdown/static/lib/highlight/styles/atelier-dune.dark.css
odoo_addons/web_widget_text_markdown/static/lib/highlight/styles/atelier-dune.light.css
odoo_addons/web_widget_text_markdown/static/lib/highlight/styles/atelier-forest.dark.css
odoo_addons/web_widget_text_markdown/static/lib/highlight/styles/atelier-forest.light.css
odoo_addons/web_widget_text_markdown/static/lib/highlight/styles/atelier-heath.dark.css
odoo_addons/web_widget_text_markdown/static/lib/highlight/styles/atelier-heath.light.css
odoo_addons/web_widget_text_markdown/static/lib/highlight/styles/atelier-lakeside.dark.css
